retask/__init__.py
retask/exceptions.py
retask/queue.py
retask/task.py
retask-1.1.0.dist-info/LICENSE
retask-1.1.0.dist-info/WHEEL
retask-1.1.0.dist-info/METADATA
retask-1.1.0.dist-info/RECORD
