Metadata-Version: 2.1
Name: retask
Version: 1.1.0
Summary: Task Queue implementation in python using redis.
Author-email: Kushal Das <mail@kushaldas.in>
Requires-Python: >=3.9
Classifier: Development Status :: 6 - Mature
Classifier: Topic :: Software Development :: Libraries
Classifier: License :: OSI Approved :: MIT License
Classifier: Topic :: System :: Distributed Computing
Classifier: Programming Language :: Python :: 3.9
Classifier: Programming Language :: Python :: 3.10
Classifier: Programming Language :: Python :: 3.11
Requires-Dist: redis
Project-URL: Documentation, https://retask.readthedocs.io/en/latest/
Project-URL: Source, https://github.com/kushaldas/retask
